parsefmt/__init__.py
parsefmt/fmtreader.py
parse_fmt-0.5.2.dist-info/LICENSE
parse_fmt-0.5.2.dist-info/METADATA
parse_fmt-0.5.2.dist-info/WHEEL
parse_fmt-0.5.2.dist-info/top_level.txt
parse_fmt-0.5.2.dist-info/RECORD
